MANIFEST.in
README.md
setup.py
codeGenD/__init__.py
codeGenD.egg-info/PKG-INFO
codeGenD.egg-info/SOURCES.txt
codeGenD.egg-info/dependency_links.txt
codeGenD.egg-info/top_level.txt
codeGenD/basic/__init__.py
codeGenD/basic/cgBasic.py
codeGenD/interface/__init__.py
codeGenD/interface/interface.py
codeGenD/test/__init__.py
codeGenD/test/test.py
codeGenD/usrLib/__init__.py
codeGenD/usrLib/cDict.json
codeGenD/usrLib/codeUnitMethod.py
codeGenD/usrLib/cppDict.json
codeGenD/usrLib/dictC.py
codeGenD/usrLib/dictCpp.py
codeGenD/usrLib/dictProvider.py
codeGenD/usrLib/dictPython.py
codeGenD/usrLib/pyDict.json
codeGenD/usrLib/snippts.py
codeGenD/usrMethod/__init__.py
codeGenD/usrMethod/codeGenC.py
codeGenD/usrMethod/codeGenCpp.py
codeGenD/usrMethod/codeGenMethod.py
codeGenD/usrMethod/codeGenPy.py
codeGenD/usrMethod/readmeMaterial.py