Metadata-Version: 2.1
Name: codeGenD
Version: 0.0.8
Summary: A tiny code generate module
Home-page: https://github.com/littleepsilon/codeGenD
Author: David Young
Author-email: david_young11@163.com
License: UNKNOWN
Platform: UNKNOWN
Classifier: Programming Language :: Python :: 3
Classifier: License :: OSI Approved :: MIT License
Classifier: Operating System :: OS Independent
